ilc_provider/__init__.py
ilc_provider/py.typed
ilc_provider-0.1.3.dist-info/METADATA
ilc_provider-0.1.3.dist-info/WHEEL
ilc_provider-0.1.3.dist-info/licenses/LICENSE.txt
ilc_provider-0.1.3.dist-info/RECORD
