Metadata-Version: 2.4
Name: ilc-provider
Version: 0.1.3
Summary: Faker provider for ILC data models
Project-URL: Repository, https://github.com/fourtreestech/ilc-provider
Project-URL: Documentation, https://ilc-provider.readthedocs.io/
Author-email: Neil Martin <neil@fourtrees.tech>
License-Expression: MIT
License-File: LICENSE.txt
Classifier: Development Status :: 4 - Beta
Classifier: Intended Audience :: Developers
Classifier: Natural Language :: English
Classifier: Programming Language :: Python :: 3.12
Classifier: Programming Language :: Python :: 3.13
Classifier: Topic :: Software Development :: Libraries
Classifier: Typing :: Typed
Requires-Python: >=3.12
Requires-Dist: faker>=37.0.2
Requires-Dist: ilc-models>=0.1.1
